README
setup.py
petlib/__init__.py
petlib/bindings.py
petlib/bn.py
petlib/cipher.py
petlib/compile.py
petlib/ec.py
petlib/ecdsa.py
petlib/hmac.py
petlib/pack.py
petlib.egg-info/PKG-INFO
petlib.egg-info/SOURCES.txt
petlib.egg-info/dependency_links.txt
petlib.egg-info/not-zip-safe
petlib.egg-info/requires.txt
petlib.egg-info/top_level.txt